{
    "animes": {
        "Tower_of_God": {
            "title": "Tower of God",
            "imagen": "https://cdn-eu.anidb.net/images/main/305415.jpg",
            "sinopsis": "Oujinaru parece no poder pasar del vigésimo piso. A pesar de fracasar una y otra vez, se niega a rendirse. En su camino, se encuentra con un personaje misterioso y poderoso llamado Viole. Wangnan invita a Viole a unirse a su equipo de Regulares. Su viaje continúa con nuevos desafíos en cada esquina.",
            "cap_total": 13,
            "temporada": 2,
            "clasificacion": "#Aventura #Acción #Drama",
            "capitulos": {
                "1": "https://uploads.overwolf.com/owclient/direct/2024/07/07/f03a364b-46db-4f6c-a435-f1100b547859.mp4",
                "2": "https://uploads.overwolf.com/owclient/direct/2024/07/14/d9903682-a431-4e07-80d7-55be479f9df3.mp4",
                "3": "https://uploads.overwolf.com/owclient/direct/2024/07/21/5b381a2e-e202-4925-846c-7dbf41afb9e0.mp4",
                "4": "https://uploads.overwolf.com/owclient/direct/2024/07/28/28654936-cd49-46aa-8889-793c58250d52.mp4",
                "5": "https://uploads.overwolf.com/owclient/direct/2024/08/04/5e386177-045b-4300-b7f3-c49e62978afa.mp4",
                "6": "https://uploads.overwolf.com/owclient/direct/2024/08/11/530df3f3-67b4-4bbd-a6d6-2f5cad7e2760.mp4",
                "7": "https://uploads.overwolf.com/owclient/direct/2024/08/18/f47bcf50-38b4-4224-8457-8ee1c18f8c6c.mp4"
            }
        },
        "Tsue_to_Tsurugi_no_Wistoria": {
            "title": "Tsue to Tsurugi no Wistoria",
            "imagen": "https://cdn-eu.anidb.net/images/main/305533.jpg",
            "sinopsis": "Will, un chico trabajador, ingresa a una academia de magia con la esperanza de convertirse en un gran hechicero. Sin embargo, hay un fatal problema en su plan: carece de la habilidad para usar magia. En medio de las miradas frías de sus compañeros y instructores, Will se siente desanimado en ocasiones, pero avanza con determinación inquebrantable. No puede usar una varita, pero puede empuñar una espada en su batalla por alcanzar la cima de un mundo dominado por la magia. Solo necesita creer en sus propias fortalezas únicas y recordar la promesa que hizo con alguien preciado para él...",
            "temporada": 1,
            "clasificacion": "#Aventura #Acción #Escolar #Fantasia",
            "cap_total": 12,
            "capitulos": {
                "1": "https://uploads.overwolf.com/owclient/direct/2024/07/07/42b691ff-5e18-4db5-b81d-3430e07d1e2a.mp4",
                "2": "https://uploads.overwolf.com/owclient/direct/2024/07/14/916f7cd2-434e-40f8-9b14-259dcb44578e.mp4",
                "3": "https://uploads.overwolf.com/owclient/direct/2024/07/21/ff4dcae1-4865-4f44-a3ef-ecc2423abcb5.mp4",
                "4": "https://uploads.overwolf.com/owclient/direct/2024/08/04/216a31f2-1b63-4e48-b2c8-7e80926f9baf.mp4",
                "5": "https://uploads.overwolf.com/owclient/direct/2024/08/11/489512de-3479-4354-bbc3-2091a40873c1.mp4",
                "6": "https://uploads.overwolf.com/owclient/direct/2024/08/18/ad9e5d2e-3b5a-4687-82ac-2d490b64fde6.mp4",
                "7": "https://uploads.overwolf.com/owclient/direct/2024/08/25/6dd23eed-48e3-49aa-ae5a-599e09290e76.mp4"
            }
        },
        "Nige_Jouzu_no_Wakagimi": {
            "title": "Nige Jouzu no Wakagimi",
            "imagen": "https://cdn-eu.anidb.net/images/main/297215.jpg",
            "sinopsis": "Tokiyuki Houjou, un niño de ocho años y el próximo sucesor del shogunato de Kamakura, carece de talento en todo excepto en jugar al escondite. Un día, su vida despreocupada da un giro abrupto cuando Takauji Ashikaga arrebata brutalmente el poder de los Kamakura, poniendo fin a su reinado. Rescatado por un sacerdote autoproclamado profético, Tokiyuki logra escapar con vida. Ahora debe evadir a aquellos que intentan matarlo mientras recluta compañeros que puedan ayudarlo a restaurar el shogunato de Kamakura a su antigua gloria.\n\nAmbientada durante el período Nanboku-chou de la historia japonesa, Nige Jouzu no Wakagimi es una historia de redención que documenta la vida del héroe olvidado que alteró el destino de Japón al huir.",
            "temporada": 1,
            "clasificacion": "#Aventura #Acción #Comedia",
            "cap_total": 12,
            "capitulos": {
                "1": "https://uploads.overwolf.com/owclient/direct/2024/07/06/a756de6b-c54a-494e-9e6f-9f7517d65371.mp4",
                "2": "https://uploads.overwolf.com/owclient/direct/2024/07/13/680c2c18-8866-41c6-a882-033847fd7299.mp4",
                "3": "https://uploads.overwolf.com/owclient/direct/2024/07/20/6f258e70-23f9-412a-8f63-0592c4452ee4.mp4",
                "4": "https://uploads.overwolf.com/owclient/direct/2024/07/27/a67694df-1c27-420b-9b08-e8390ea137ba.mp4",
                "5": "https://uploads.overwolf.com/owclient/direct/2024/08/03/4bee579f-788e-4df9-8da5-a329af4d4e15.mp4",
                "6": "https://uploads.overwolf.com/owclient/direct/2024/08/10/17057a24-f299-4634-a243-ea17e92cae26.mp4",
                "7": "https://uploads.overwolf.com/owclient/direct/2024/08/17/393d1a2b-b98a-460c-b3fe-639f851b6f69.mp4",
                "8": "https://uploads.overwolf.com/owclient/direct/2024/08/24/8bf2a2e8-ab01-4e4f-861a-db8fe5914d33.mp4"
            }
        },
        "Suicide_Squad_Isekai": {
            "title": "Suicide Squad Isekai",
            "imagen": "https://cdn-eu.anidb.net/images/main/304978.jpg",
            "sinopsis": " ¡Una fiesta loca y mortal de los villanos más malos llega a un isekai!\n¡La aventura fantástica más peligrosa y extraña revelada…!!!\n¡Harley Quinn y El Joker de DC han sido transportados a un ISEKAI! ¡El Escuadrón Suicida se desata en el escenario de un ISEKAI!\n¡Una nueva animación original de Japón! ¡Los mundos más alucinantes colisionan en una fantasía épica y violenta con el equipo de creadores más fuerte!",
            "temporada": 1,
            "clasificacion": "#Aventura #Acción #Isekai",
            "cap_total": 10,
            "capitulos": {
                "1": "https://uploads.overwolf.com/owclient/direct/2024/06/27/5f793d58-b283-449b-87e9-85efcecce842.mp4",
                "2": "https://uploads.overwolf.com/owclient/direct/2024/06/27/e2970be2-a851-4c43-b5f1-45b54b601a94.mp4",
                "3": "https://uploads.overwolf.com/owclient/direct/2024/06/27/0b4bfea7-5354-423f-ad1e-f713bf862bff.mp4",
                "4": "https://uploads.overwolf.com/owclient/direct/2024/07/04/8ff7d327-8930-467c-8837-7ed723503636.mp4",
                "5": "https://uploads.overwolf.com/owclient/direct/2024/07/11/44311925-5922-4d03-a600-e98ab86f32fc.mp4",
                "6": "https://uploads.overwolf.com/owclient/direct/2024/07/18/5ab30b7d-4178-4b5b-a5e1-4b3445cb91bb.mp4",
                "7": "https://uploads.overwolf.com/owclient/direct/2024/07/25/94ecbeec-9eb2-4ddd-a8f3-503f093b58da.mp4",
                "8": "https://uploads.overwolf.com/owclient/direct/2024/08/01/1e62483e-4868-4511-b7dc-433396551e7e.mp4",
                "9": "https://uploads.overwolf.com/owclient/direct/2024/08/08/b22ce7a5-5020-48ce-b61f-4280e51ae5d7.mp4",
                "10": "https://uploads.overwolf.com/owclient/direct/2024/08/15/a959a01d-cbf8-45b2-8057-b42aa52ddf56.mp4"
            }
        },
        "NieR:Automata_Ver1.1a_Parte_2": {
            "title": "NieR:Automata Ver1.1a Parte 2",
            "imagen": "https://cdn-eu.anidb.net/images/main/305068.jpg",
            "sinopsis": "El futuro distante, 5012. La repentina invasión aérea de la Tierra por parte de alienígenas y sus creaciones, los Formas de Vida Máquina, llevó a la humanidad al borde de la extinción. El número reducido de humanos que se refugiaron en la luna organizaron un contraataque utilizando soldados androides para recapturar la Tierra. Sin embargo, la guerra llega a un punto muerto ya que las Formas de Vida Máquina continúan multiplicándose infinitamente. A su vez, la humanidad despliega una nueva unidad de soldados androides en la Tierra como arma definitiva: YoRHa.\nEl año 11954, los soldados de YoRHa 2B y 9S son enviados a la Tierra para llevar a cabo y apoyar la 243ª Operación de Descenso. Allí, logran destruir las unidades centrales de las formas de vida máquina, Adam y Eve. Con la aniquilación de estos enemigos, el Ejército de la Humanidad toma esta oportunidad para poner fin a esta guerra que se prolonga y decide lanzar un ataque total contra las formas de vida máquina.\nEste es un registro de las batallas y esperanzas de los androides y del destino que los dicta a todos...",
            "temporada": 2,
            "clasificacion": "#Aventura #Acción #Drama",
            "cap_total": 12,
            "capitulos": {
                "1": "https://uploads.overwolf.com/owclient/direct/2024/07/05/8984fcf0-7706-4469-be60-5009ac7819f9.mp4",
                "2": "https://uploads.overwolf.com/owclient/direct/2024/07/12/8176a182-535d-497a-8c81-77f425507c81.mp4",
                "3": "https://uploads.overwolf.com/owclient/direct/2024/07/19/dcdd0c98-7db3-4415-9474-1edeac35d934.mp4",
                "4": "https://uploads.overwolf.com/owclient/direct/2024/07/26/c872110c-c4ce-4891-8ae0-45736aa26b17.mp4",
                "5": "https://uploads.overwolf.com/owclient/direct/2024/08/02/e0f613c9-98e0-4d1b-ab4d-579febbcb1f1.mp4",
                "6": "https://uploads.overwolf.com/owclient/direct/2024/08/09/1539a877-e919-4197-a73c-40690cba3318.mp4",
                "7": "https://uploads.overwolf.com/owclient/direct/2024/08/23/a7baa437-6051-45b5-89d5-79716372be01.mp4"
            }
        },
        "Tensei_Shitara_Dai_Nana_Ouji_Dattan": {
            "title": "Tensei Shitara Dai Nana Ouji Datta",
            "imagen": "https://cdn-eu.anidb.net/images/main/299446.jpg",
            "sinopsis": "El príncipe Lloyd no siempre fue un príncipe... de hecho, su vida anterior es algo que recuerda perfectamente: era un tipo de hechicero. Así que, cuando lo obligaron a reencarnarse, decidió seguir con sus estudios, ¡príncipe del reino o no! Pero su nueva vida tiene sus propios desafíos... ¡incluyendo ser un niño de 10 años! ¿Qué puede hacer el séptimo príncipe/hechicero?",
            "temporada": 1,
            "clasificacion": "#Aventura #Isekai #Fantasia",
            "cap_total": 12,
            "capitulos": {
                "1": "https://uploads.overwolf.com/owclient/direct/2024/04/01/e51f2e2c-b8e9-41ef-8fbb-dae6525d70ff.mp4",
                "2": "https://uploads.overwolf.com/owclient/direct/2024/04/08/87550843-edd0-4b23-a821-5c0d81a28baa.mp4",
                "3": "https://uploads.overwolf.com/owclient/direct/2024/04/15/53b4aba8-36f5-4aac-aab7-2965533417a9.mp4",
                "4": "https://uploads.overwolf.com/owclient/direct/2024/04/22/8bb11dfc-b18d-4a8d-b526-ac6c6c8a7270.mp4",
                "5": "https://uploads.overwolf.com/owclient/direct/2024/04/29/fd2261fc-2693-4a80-b744-fabdef465a50.mp4",
                "6": "https://uploads.overwolf.com/owclient/direct/2024/05/06/d6c27074-28b9-4192-9173-35c217876c53.mp4",
                "7": "https://uploads.overwolf.com/owclient/direct/2024/05/13/f5e3e1b7-833e-4722-b729-27043505ba06.mp4",
                "8": "https://uploads.overwolf.com/owclient/direct/2024/05/20/9a558d4e-9328-4ab0-96f1-20e51bdb8fca.mp4",
                "9": "https://uploads.overwolf.com/owclient/direct/2024/05/27/8f45b315-7b4c-44eb-84a5-d39ccb3d051a.mp4",
                "10": "https://uploads.overwolf.com/owclient/direct/2024/06/03/b7070d83-db51-4284-903e-7374971de0b8.mp4",
                "11": "https://uploads.overwolf.com/owclient/direct/2024/06/10/45dfe398-8052-4d76-8dc2-d77886e89b83.mp4",
                "12": "https://uploads.overwolf.com/owclient/direct/2024/06/17/fecc85ec-f0a6-41c2-bf99-1a870622e8c1.mp4"
            }
        },
        "Kimetsu_no_Yaiba:_Hashira_Geiko_Hen": {
            "title": "Kimetsu no Yaiba: Hashira Geiko Hen",
            "imagen": "https://cdn-eu.anidb.net/images/main/303614.jpg",
            "sinopsis": "",
            "temporada": 4,
            "clasificacion": "#Aventura #Acción #Fantasia",
            "cap_total": 8,
            "capitulos": {
                "1": "https://uploads.overwolf.com/owclient/direct/2024/05/12/b890e407-4447-48b3-a525-43f5bb1d425f.mp4",
                "2": "https://uploads.overwolf.com/owclient/direct/2024/05/19/7564803f-060d-4002-9d2f-3d71f960017a.mp4",
                "3": "https://uploads.overwolf.com/owclient/direct/2024/05/26/0e2c3cbe-083c-4f6f-b829-16c53f313733.mp4",
                "4": "https://uploads.overwolf.com/owclient/direct/2024/06/02/b141d4a5-7edf-4f4f-bb9f-98b5ddf1a8c8.mp4",
                "5": "https://uploads.overwolf.com/owclient/direct/2024/06/09/a97b9b65-cd4c-404a-8c59-47881e5a092f.mp4",
                "6": "https://uploads.overwolf.com/owclient/direct/2024/06/16/f71b0294-3a85-41bb-99f5-db859bb0850a.mp4",
                "7": "https://uploads.overwolf.com/owclient/direct/2024/06/23/c7ec00ad-3688-43e0-bece-bca46d84516a.mp4",
                "8": "https://uploads.overwolf.com/owclient/direct/2024/06/30/3f61fdf9-807d-49ff-b6cd-749fb7153cdc.mp4"
            }
        },
        "Shangri-La_Frontier:_Kusogee_Hunter,_Kamige_ni_Idoman_to_Su": {
            "title": "Shangri-La Frontier: Kusogee Hunter, Kamige ni Idoman to Su",
            "imagen": "https://cdn-eu.anidb.net/images/main/293673.jpg",
            "sinopsis": "El estudiante de segundo año de secundaria Hizutome Rakurou solo está interesado en una cosa: encontrar \"juegos de mierda\" y darles una paliza. Sus habilidades en los videojuegos son inigualables, y ningún juego es tan malo que no pueda disfrutarlo. Así que cuando le presentan el nuevo juego de VR Shangri-La Frontier, hace lo que mejor sabe hacer: optimizar y salta el prólogo para ir directo a la acción. Pero, ¿podrá incluso un gamer experto como Rakurou descubrir todos los secretos que esconde Shangri-La Frontier…?",
            "temporada": 1,
            "clasificacion": "#Aventura #Accíon",
            "cap_total": 25,
            "capitulos": {
                "1": "https://uploads.overwolf.com/owclient/direct/2023/10/09/f4a9acad-c1ed-4236-b715-9dd35696648f.mp4",
                "2": "https://uploads.overwolf.com/owclient/direct/2023/10/09/d0265575-c0a2-4345-a43d-6e80851fdd52.mp4",
                "3": "https://uploads.overwolf.com/owclient/direct/2023/10/15/e1b7c3c4-6025-4c69-9a94-ef5a03cf7982.mp4",
                "4": "https://uploads.overwolf.com/owclient/direct/2023/10/22/84394e5a-6d33-4661-a866-8541c311458f.mp4",
                "5": "https://uploads.overwolf.com/owclient/direct/2023/10/29/299bb47d-b3a2-462a-8515-524a253086b9.mp4",
                "6": "https://uploads.overwolf.com/owclient/direct/2023/11/05/3d5c2a96-d5e5-4310-a371-b16ebd249248.mp4",
                "7": "https://uploads.overwolf.com/owclient/direct/2023/11/12/43faa078-dec6-46e0-b736-c6a2a83f2d85.mp4",
                "8": "https://uploads.overwolf.com/owclient/direct/2023/11/19/d2a7f305-67bb-4256-b773-710990a465af.mp4",
                "9": "https://uploads.overwolf.com/owclient/direct/2023/11/26/b11e0219-408b-4d16-9180-2cd0ffe67012.mp4",
                "10": "https://uploads.overwolf.com/owclient/direct/2023/12/03/04de4138-063a-425d-9681-a659612eddb0.mp4",
                "11": "https://uploads.overwolf.com/owclient/direct/2023/12/10/60f69a70-5106-434a-8d81-70d141ce6ad7.mp4",
                "12": "https://uploads.overwolf.com/owclient/direct/2023/12/17/01066bc2-5d34-463f-b7cc-8af4d76c2158.mp4",
                "13": "https://uploads.overwolf.com/owclient/direct/2023/12/24/e49fe8ee-96ec-4e75-940a-f14bed1e7a28.mp4",
                "14": "https://uploads.overwolf.com/owclient/direct/2024/01/07/95a80a6b-0f98-4c18-ba85-e60ca8ee87ce.mp4",
                "15": "https://uploads.overwolf.com/owclient/direct/2024/01/21/d49aa2c0-2b3b-413b-8ab8-3da0656e951f.mp4",
                "16": "https://uploads.overwolf.com/owclient/direct/2024/01/28/22d8d5a1-a8fb-4c8c-ba51-7d15a2934c65.mp4",
                "17": "https://uploads.overwolf.com/owclient/direct/2024/02/04/4a530a0c-3706-4814-8297-d1131a91c77e.mp4",
                "18": "https://uploads.overwolf.com/owclient/direct/2024/02/11/61682cde-a0b2-4650-9f11-a529cd2744bb.mp4",
                "19": "https://uploads.overwolf.com/owclient/direct/2024/02/18/9d39fbce-eb50-4595-bc76-f4c3c9c985bd.mp4",
                "20": "https://uploads.overwolf.com/owclient/direct/2024/02/25/c9c46091-99b1-4511-ba09-2c75f91d7e85.mp4",
                "21": "https://uploads.overwolf.com/owclient/direct/2024/03/03/76adbbfb-f56d-4b67-a496-914eea5bea1e.mp4",
                "22": "https://uploads.overwolf.com/owclient/direct/2024/03/10/00cd9d0e-b1b3-41bc-acc5-8e1fdc04fc2a.mp4",
                "23": "https://uploads.overwolf.com/owclient/direct/2024/03/17/f2802f03-62b7-49bb-98c7-ae6e5866d7c0.mp4",
                "24": "https://uploads.overwolf.com/owclient/direct/2024/03/24/20a8aa26-e50e-4f54-ba89-4129d801a7f3.mp4",
                "25": "https://uploads.overwolf.com/owclient/direct/2024/03/31/b4ffbbc4-ce83-40d3-b8d6-2739913ee6be.mp4"
            }
        },
        "Solo_Leveling": {
            "title": "Solo Leveling",
            "imagen": "https://cdn-eu.anidb.net/images/main/294410.jpg",
            "sinopsis": "Conocido como el Cazador Más Débil de toda la humanidad, el cazador de rango E, Jinwoo Sung, solo aporta a las incursiones intentando no acabar muerto. Lamentablemente, entre las facturas del hospital de su madre, la matrícula de su hermana y su propia falta de perspectivas laborales, no tiene más opción que seguir arriesgando su vida. Así que, cuando surge la oportunidad de una recompensa mayor, la aprovecha... ¡solo para encontrarse cara a cara con un ser cuyo poder supera todo lo que ha visto antes! Con el líder del grupo sin un brazo y el único sanador siendo un desastre tembloroso, ¿podrá Jinwoo encontrar de alguna manera una salida para ellos?",
            "temporada": 1,
            "clasificacion": "#Aventura #Fantasia",
            "cap_total": 12,
            "capitulos": {
                "1": "https://uploads.overwolf.com/owclient/direct/2024/01/06/0fdcd769-8b83-4683-9a09-20b454481169.mp4",
                "2": "https://uploads.overwolf.com/owclient/direct/2024/01/13/39cfd736-e74d-4edb-8406-08f0b8997260.mp4",
                "3": "https://uploads.overwolf.com/owclient/direct/2024/01/20/efefeeff-9fcb-4aca-8cfc-b1b23766355f.mp4",
                "4": "https://uploads.overwolf.com/owclient/direct/2024/01/27/7eaace6b-43c0-45af-ad91-c0f3467bc0c9.mp4",
                "5": "https://uploads.overwolf.com/owclient/direct/2024/02/03/511abba4-c972-46b4-a14d-abc64ab984e4.mp4",
                "6": "https://uploads.overwolf.com/owclient/direct/2024/02/10/0b55b245-d42a-456f-b775-ced7f4349e36.mp4",
                "7": "https://uploads.overwolf.com/owclient/direct/2024/02/17/e845a73d-6ef5-47dd-b7ac-cd639e21d627.mp4",
                "8": "https://uploads.overwolf.com/owclient/direct/2024/03/02/155b8ae7-7a48-4ee6-8969-6d35c60addde.mp4",
                "9": "https://uploads.overwolf.com/owclient/direct/2024/03/09/d0d58632-1610-4f4f-bca0-65a58b8015e9.mp4",
                "10": "https://uploads.overwolf.com/owclient/direct/2024/03/16/344f7a8f-af4a-4c80-a70d-21571c5482b7.mp4",
                "11": "https://uploads.overwolf.com/owclient/direct/2024/03/23/02fd0f5d-7461-4a9a-8b73-49106bbae985.mp4",
                "12": "https://uploads.overwolf.com/owclient/direct/2024/03/30/03cd2db2-d478-4cf6-88c7-c50a261fbd98.mp4"
            }
        },
        "Sousou_no_Frieren": {
            "title": "Sousou no Frieren",
            "imagen": "https://cdn-eu.anidb.net/images/main/295082.jpg",
            "sinopsis": "La maga elfa Frieren y sus valientes compañeros aventureros han derrotado al Rey Demonio y traído paz a la tierra. Con la gran lucha superada, cada uno toma su propio camino para vivir una vida tranquila. Pero como elfa, Frieren, casi inmortal, superará con creces a los demás miembros de su antiguo grupo. ¿Cómo aceptará la mortalidad de sus amigos? ¿Cómo puede encontrar satisfacción en su propia vida, y puede aprender a comprender lo que significa la vida para los humanos a su alrededor? Frieren comienza un nuevo viaje para encontrar la respuesta.",
            "temporada": 1,
            "clasificacion": "#Aventura #Fantasia #Drama",
            "cap_total": 28,
            "capitulos": {
                "1": "https://uploads.overwolf.com/owclient/direct/2023/10/06/aaf25282-f3d3-4900-8ee2-df806e72afe2.mp4",
                "2": "https://uploads.overwolf.com/owclient/direct/2023/10/06/65833746-472a-4446-88f0-61d3ce04d4dc.mp4",
                "3": "https://uploads.overwolf.com/owclient/direct/2023/10/06/8fb76802-ba0c-4d22-90ce-d24996f7e164.mp4",
                "4": "https://uploads.overwolf.com/owclient/direct/2023/10/06/d8699514-163c-4f12-984f-5f40eb7d805b.mp4",
                "5": "https://uploads.overwolf.com/owclient/direct/2023/10/06/a2d146de-3f97-4ec8-b032-489b66d84488.mp4",
                "6": "https://uploads.overwolf.com/owclient/direct/2023/10/13/4626d32a-b7b6-4396-88db-27de0ba8e329.mp4",
                "7": "https://uploads.overwolf.com/owclient/direct/2023/11/05/a6063f6c-2057-4073-8e10-9f1ae2b22cb9.mp4",
                "8": "https://uploads.overwolf.com/owclient/direct/2023/10/27/b53b86f6-73ab-424c-962c-44a542d74deb.mp4",
                "9": "https://uploads.overwolf.com/owclient/direct/2023/11/03/324df6e6-17fc-44bb-a547-7d4dd2778702.mp4",
                "10": "https://uploads.overwolf.com/owclient/direct/2023/11/10/2a681b56-37ca-4d5e-8a79-9b411373b8fd.mp4",
                "11": "https://uploads.overwolf.com/owclient/direct/2023/11/17/8f3ccb4d-15ce-4aba-8b28-b820789095f1.mp4",
                "12": "https://uploads.overwolf.com/owclient/direct/2023/11/24/ed2a846c-e4d4-470e-8bf4-2c5cdecc438e.mp4",
                "13": "https://uploads.overwolf.com/owclient/direct/2023/12/03/fb15e2d4-6ff5-47af-b252-650106a80877.mp4",
                "14": "https://uploads.overwolf.com/owclient/direct/2023/12/08/db8f6edf-25a8-4484-bbde-f5c7cd7d2413.mp4",
                "15": "https://uploads.overwolf.com/owclient/direct/2023/12/15/1bfee945-9672-44fb-8793-94ac99b1a342.mp4",
                "16": "https://uploads.overwolf.com/owclient/direct/2023/12/22/70d3136c-7216-4360-b2fe-1e9b487eb470.mp4",
                "17": "https://uploads.overwolf.com/owclient/direct/2024/01/05/80b935b7-2a54-4609-9bee-a0fe43d11e51.mp4",
                "18": "https://uploads.overwolf.com/owclient/direct/2024/01/12/313f1210-6730-4f6a-bc60-0f433ad43046.mp4",
                "19": "https://uploads.overwolf.com/owclient/direct/2024/01/19/667d2c03-0062-48ca-b841-1ea65ba80f22.mp4",
                "20": "https://uploads.overwolf.com/owclient/direct/2024/01/26/3bc46898-c64e-4a24-987d-17ec6aeaab05.mp4",
                "21": "https://uploads.overwolf.com/owclient/direct/2024/02/02/d24d3726-60da-425c-8d6a-8cddf26788cf.mp4",
                "22": "https://uploads.overwolf.com/owclient/direct/2024/02/09/4775a8a0-939c-4264-9987-70f49e7bfe28.mp4",
                "23": "https://uploads.overwolf.com/owclient/direct/2024/02/16/632ce41a-83cd-4fc9-9eec-0c1516e80689.mp4",
                "24": "https://uploads.overwolf.com/owclient/direct/2024/03/01/66b13ef7-3e88-4068-91c4-c3197ac63230.mp4",
                "25": "https://uploads.overwolf.com/owclient/direct/2024/03/01/3917a053-6d94-4bfb-aa61-a28334570f95.mp4",
                "26": "https://uploads.overwolf.com/owclient/direct/2024/03/08/74f189d4-50c9-420f-b7aa-a0c67b177609.mp4",
                "27": "https://uploads.overwolf.com/owclient/direct/2024/03/15/d77991b2-49ce-4bef-b061-97722c96b3ae.mp4",
                "28": "https://uploads.overwolf.com/owclient/direct/2024/03/22/7323c8fa-9125-429f-9ddb-962ba0368484.mp4"
            }
        },
        "Kaijuu_8-gou": {
            "title": "Kaijuu 8-gou",
            "imagen": "https://cdn-eu.anidb.net/images/main/297170.jpg",
            "sinopsis": "Con las tasas más altas de aparición de kaiju en el mundo, Japón no es extraño a los ataques de monstruos mortales. Entra la Fuerza de Defensa de Japón, una organización militar encargada de neutralizar a los kaiju. Hibino Kafka, un limpiador de cadáveres de kaiju, siempre ha soñado con unirse a la fuerza. Pero cuando tiene otra oportunidad de cumplir su sueño de infancia, sufre una transformación inesperada. ¡¿Cómo puede luchar contra los kaiju ahora que él mismo se ha convertido en uno?!",
            "temporada": 1,
            "clasificacion": "#ficción #Acción",
            "cap_total": 12,
            "capitulos": {
                "1": "https://uploads.overwolf.com/owclient/direct/2024/04/13/420582b1-043b-4425-9dde-f4be57009e39.mp4",
                "2": "https://uploads.overwolf.com/owclient/direct/2024/04/20/393fb8e3-17e4-4618-b205-8cd3b5b84dc2.mp4",
                "3": "https://uploads.overwolf.com/owclient/direct/2024/04/27/5520090c-81f8-45a1-b3b5-b6e8645516aa.mp4",
                "4": "https://uploads.overwolf.com/owclient/direct/2024/05/04/90eb533a-a19a-4df9-aa9c-afab630b0f2a.mp4",
                "5": "https://uploads.overwolf.com/owclient/direct/2024/05/11/86be036d-d30f-4edf-87e4-651bd2249bd2.mp4",
                "6": "https://uploads.overwolf.com/owclient/direct/2024/05/18/6d397540-bf91-4e8e-a57a-96a853e27066.mp4",
                "7": "https://uploads.overwolf.com/owclient/direct/2024/05/25/b1ce2ecf-339b-43c6-9791-25b530533648.mp4",
                "8": "https://uploads.overwolf.com/owclient/direct/2024/06/01/babe800a-c060-4f14-b0df-92c923a4c4ea.mp4",
                "9": "https://uploads.overwolf.com/owclient/direct/2024/06/08/2ebf9529-fdf3-4ef9-b904-e79d20749719.mp4",
                "10": "https://uploads.overwolf.com/owclient/direct/2024/06/15/1f80f165-2fe4-4828-91b8-3b74a68a52e4.mp4",
                "11": "https://uploads.overwolf.com/owclient/direct/2024/06/22/eb1baaba-b65d-48db-b05e-547742aba325.mp4",
                "12": "https://uploads.overwolf.com/owclient/direct/2024/06/29/1b704cf3-15b3-4ea4-b069-45cf681fc07f.mp4"
            }
        },
        "Ninja_Kamui": {
            "title": "Ninja Kamui",
            "imagen": "https://cdn-eu.anidb.net/images/main/302958.jpg",
            "sinopsis": "Joe Higan es un Nukenin, un antiguo ninja que escapó de su clan y se esconde de su violento pasado en una zona rural de América con su familia. Una noche, es emboscado por un equipo de asesinos de su antigua organización que llevan a cabo una sangrienta venganza contra Joe y su familia por traicionar su antiguo código. Resurgiendo de su aparente \"muerte\", Joe volverá a ser su antiguo yo – Ninja Kamui – para vengar a su familia y amigos. Kamui es un ninja del siglo XXI, un anacronismo sombrío que enfrenta sus habilidades ancestrales contra armamento de alta tecnología con brutal destreza. Él debe enfrentarse a asesinos entrenados, cyborgs de combate y ninjas rivales para derribar al mismo clan que lo creó.",
            "temporada": 1,
            "clasificacion": "#acción #Aventura #Drama",
            "cap_total": 13,
            "capitulos": {
                "1": "https://uploads.overwolf.com/owclient/direct/2024/02/11/ac771347-32bf-4e72-999b-512be1683725.mp4",
                "2": "https://uploads.overwolf.com/owclient/direct/2024/02/18/0ee0e331-92cd-4e26-bbde-f7716d3fc311.mp4",
                "3": "https://uploads.overwolf.com/owclient/direct/2024/02/25/4372ab52-52bf-4cc2-93b9-169f54cb3eb7.mp4",
                "4": "https://uploads.overwolf.com/owclient/direct/2024/03/03/b4e01122-1c17-42b2-a5d7-3547602db249.mp4",
                "5": "https://uploads.overwolf.com/owclient/direct/2024/03/10/4b255171-5148-4277-983e-be9bac36df65.mp4",
                "6": "https://uploads.overwolf.com/owclient/direct/2024/03/17/e1e7ec77-b337-4c81-96d2-f41cb75807f5.mp4",
                "7": "https://uploads.overwolf.com/owclient/direct/2024/03/24/e11c8bb3-6ea8-456c-a2d4-dda3b1c297be.mp4",
                "8": "https://uploads.overwolf.com/owclient/direct/2024/03/31/d376e625-b97b-4b3e-996d-3dac40ba2add.mp4",
                "9": "https://uploads.overwolf.com/owclient/direct/2024/04/07/e5cbed26-e7b2-4b0b-8f22-a2568a616810.mp4",
                "10": "https://uploads.overwolf.com/owclient/direct/2024/04/14/9d24959f-db46-4b05-ad52-3fe7e1113f16.mp4",
                "11": "https://uploads.overwolf.com/owclient/direct/2024/04/21/dc8f548f-137e-4b7f-848b-382116d613b8.mp4",
                "12": "https://uploads.overwolf.com/owclient/direct/2024/04/28/e365f75c-b37d-46e7-9ad2-bba8441104a6.mp4",
                "13": "https://uploads.overwolf.com/owclient/direct/2024/05/05/62953d0c-4433-412e-b5f2-ff727382642b.mp4"
            }
        }
    },
    "animes_latino": {
        "Jujutsu_Kaisen": {
            "title": "Jujutsu Kaisen",
            "imagen": "https://telegra.ph/file/6526bf7ba5047a7d8703d.jpg",
            "sinopsis": "Yuuji Itadori, un estudiante de secundaria que se dedica a actividades paranormales sin fundamento en el Club de Ocultismo, pasa sus días en el salón del club o en el hospital, donde visita a su abuelo postrado en cama. Sin embargo, este estilo de vida relajado pronto se vuelve extraño cuando, sin saberlo, se encuentra con un objeto maldito. Desencadenando una cadena de sucesos sobrenaturales, Yuuji se ve repentinamente inmerso en el mundo de las Maldiciones (seres terribles formados a partir de la malicia y la negatividad humanas) después de tragarse dicho objeto, que se revela como un dedo perteneciente al demonio Sukuna Ryoumen, el Rey de las Maldiciones.\n\nYuuji experimenta de primera mano la amenaza que estas Maldiciones representan para la sociedad mientras descubre sus propios poderes recién descubiertos. Introducido en la Escuela Secundaria de Jujutsu de la Prefectura de Tokio, comienza a caminar por un camino del que no puede regresar: el camino de un hechicero de Jujutsu.",
            "cap_total": 46,
            "temporada": 1,
            "clasificacion": " #Shonen #Acción #Sobrenatural",
            "capitulos": {
                "1": "https://uploads.overwolf.com/owclient/direct/2024/08/05/6bf8f1d0-aea4-4ae7-b91c-223efc66b3f9.mp4",
                "2": "https://uploads.overwolf.com/owclient/direct/2024/08/05/09f073e3-eb42-4661-a974-4991a794b142.mp4",
                "3": "https://uploads.overwolf.com/owclient/direct/2024/08/05/9c2ad07a-6031-4fb8-9caa-304beac1b051.mp4",
                "4": "https://uploads.overwolf.com/owclient/direct/2024/08/05/80128cbd-8a40-46ee-8ec0-d72d085f5b1b.mp4",
                "5": "https://uploads.overwolf.com/owclient/direct/2024/08/05/8f9cf7d1-ad02-42da-b688-31b2ddb51668.mp4",
                "6": "https://uploads.overwolf.com/owclient/direct/2024/08/05/9d76f349-4f3c-47bf-bde1-0c5eff518958.mp4",
                "7": "https://uploads.overwolf.com/owclient/direct/2024/08/05/e8b9483c-89df-4174-8fca-15ad7ebebd35.mp4",
                "8": "https://uploads.overwolf.com/owclient/direct/2024/08/05/5ecde69a-58c8-4d39-95a3-3a0c4d010943.mp4",
                "9": "https://uploads.overwolf.com/owclient/direct/2024/08/05/08e2d9f5-dd89-450a-acd8-a31c6e30cc77.mp4",
                "10": "https://uploads.overwolf.com/owclient/direct/2024/08/06/e01d404b-c35a-4a77-8411-9110f03820b1.mp4",
                "11": "https://uploads.overwolf.com/owclient/direct/2024/08/05/1cff7277-d2d1-42a7-8cd0-95373b31c06a.mp4",
                "12": "https://uploads.overwolf.com/owclient/direct/2024/08/05/879ecbc2-fab8-45de-a775-7a02220eb27c.mp4",
                "13": "https://uploads.overwolf.com/owclient/direct/2024/08/05/fef3b7db-c830-49c5-9cf0-9d6e919a48da.mp4",
                "14": "https://uploads.overwolf.com/owclient/direct/2024/08/05/110d4010-5bc2-4793-9cab-ac9e19ec6a2b.mp4",
                "15": "https://uploads.overwolf.com/owclient/direct/2024/08/05/6d0c94b5-fd29-4174-bb45-988c1f284241.mp4",
                "16": "https://uploads.overwolf.com/owclient/direct/2024/08/05/02fee974-52a0-4197-9d9d-42bb8013a03f.mp4",
                "17": "https://uploads.overwolf.com/owclient/direct/2024/08/05/597427ca-3c24-48d5-ba96-19da97a59a8e.mp4",
                "18": "https://uploads.overwolf.com/owclient/direct/2024/08/05/0328b8ba-9dd7-4487-a0b1-7acb5e3ac6c3.mp4",
                "19": "https://uploads.overwolf.com/owclient/direct/2024/08/05/0c119e46-30ed-42d6-9ddd-17e856c63a5e.mp4",
                "20": "https://uploads.overwolf.com/owclient/direct/2024/08/05/edddabeb-c2d8-499d-89b8-147c40528198.mp4",
                "21": "https://uploads.overwolf.com/owclient/direct/2024/08/05/d20d6559-53fb-44f9-a7f9-99392c280e3c.mp4",
                "22": "https://uploads.overwolf.com/owclient/direct/2024/08/05/3c4ef23c-f2a4-4ca5-a4ab-06c628d19fb1.mp4",
                "23": "https://uploads.overwolf.com/owclient/direct/2024/08/05/ab851a8c-30e9-4a89-b1f9-13ee2e6a9daa.mp4",
                "24": "https://uploads.overwolf.com/owclient/direct/2024/08/05/3683762e-ad23-4cae-aeab-418ce2760ed6.mp4",
                "25": "https://uploads.overwolf.com/owclient/direct/2024/08/05/8c3639e9-3a5f-4c4a-94b2-163b55ac450b.mp4",
                "26": "https://uploads.overwolf.com/owclient/direct/2024/08/05/12552fc7-3770-4d6f-93fc-79a87f4e0f21.mp4",
                "27": "https://uploads.overwolf.com/owclient/direct/2024/08/05/c4208684-cd74-4bf2-aa6a-5db63c6ab314.mp4",
                "28": "https://uploads.overwolf.com/owclient/direct/2024/08/05/ad775622-9cb2-41a2-bc84-38e8f293cfa1.mp4",
                "29": "https://uploads.overwolf.com/owclient/direct/2024/08/05/44187ae7-5254-4b6d-970a-702562096ba1.mp4",
                "30": "https://uploads.overwolf.com/owclient/direct/2024/08/05/06021187-57ad-4401-9a55-be095f4739ab.mp4",
                "31": "https://uploads.overwolf.com/owclient/direct/2024/08/05/40c8a224-6e39-440e-8cee-69e1bf80ecd8.mp4",
                "32": "https://uploads.overwolf.com/owclient/direct/2024/08/05/1462b5a5-c080-4202-a55c-46a4f70b37b2.mp4",
                "33": "https://uploads.overwolf.com/owclient/direct/2024/08/05/d8697691-fb6a-42ae-914d-f2b904d08559.mp4",
                "34": "https://uploads.overwolf.com/owclient/direct/2024/08/05/e79673ee-f786-4ce9-bd96-da9ccbb539f2.mp4",
                "35": "https://uploads.overwolf.com/owclient/direct/2024/08/05/4aedf51a-565b-4992-a5f3-aa4fa1e81a0d.mp4",
                "36": "https://uploads.overwolf.com/owclient/direct/2024/08/05/e5a63b05-7729-4b54-a7c5-1a85443a6692.mp4",
                "37": "https://uploads.overwolf.com/owclient/direct/2024/08/05/22b4295c-f166-4185-8ff9-559493c68c67.mp4",
                "38": "https://uploads.overwolf.com/owclient/direct/2024/08/06/71294a15-4b05-47c2-9c4d-11be4f2631ca.mp4",
                "39": "https://uploads.overwolf.com/owclient/direct/2024/08/06/7e093621-f1c8-4890-b446-23975bf7f0d0.mp4",
                "40": "https://uploads.overwolf.com/owclient/direct/2024/08/06/df5a17fc-9b30-46ce-85bb-d4e3925bd102.mp4",
                "41": "https://uploads.overwolf.com/owclient/direct/2024/08/06/294a740b-db52-4ee6-9416-09fe87fdc6b3.mp4",
                "42": "https://uploads.overwolf.com/owclient/direct/2024/08/06/063d2b3a-92af-4bef-9fbf-4b66226ac49e.mp4",
                "43": "https://uploads.overwolf.com/owclient/direct/2024/08/06/8892530e-84d0-4ba3-a2ff-5ee033cc2462.mp4",
                "44": "https://uploads.overwolf.com/owclient/direct/2024/08/06/254c0674-4b7f-46cb-9095-a88423a8dbc2.mp4",
                "45": "https://uploads.overwolf.com/owclient/direct/2024/08/06/d120182c-34e8-41c2-971b-e90612f18caf.mp4",
                "46": "https://uploads.overwolf.com/owclient/direct/2024/08/06/6776f263-4877-4c7b-8b8c-389f9876f604.mp4"
            }
        },
        "Solo_Leveling": {
            "title": "Solo Leveling",
            "imagen": "https://cdn-eu.anidb.net/images/main/294410.jpg",
            "sinopsis": "Conocido como el Cazador Más Débil de toda la humanidad, el cazador de rango E, Jinwoo Sung, solo aporta a las incursiones intentando no acabar muerto. Lamentablemente, entre las facturas del hospital de su madre, la matrícula de su hermana y su propia falta de perspectivas laborales, no tiene más opción que seguir arriesgando su vida. Así que, cuando surge la oportunidad de una recompensa mayor, la aprovecha... ¡solo para encontrarse cara a cara con un ser cuyo poder supera todo lo que ha visto antes! Con el líder del grupo sin un brazo y el único sanador siendo un desastre tembloroso, ¿podrá Jinwoo encontrar de alguna manera una salida para ellos?",
            "temporada": 1,
            "clasificacion": "#Aventura #Fantasia",
            "cap_total": 12,
            "capitulos": {
                "1": "https://uploads.overwolf.com/owclient/direct/2024/07/23/d1736c0e-830e-46b2-befd-dbe8374d606f.mp4",
                "2": "https://uploads.overwolf.com/owclient/direct/2024/07/23/093c1fef-33f3-41d2-b9bb-90b36278dbda.mp4",
                "3": "https://uploads.overwolf.com/owclient/direct/2024/07/24/d7c75805-fc8f-4a55-aa85-afa4bba7742e.mp4",
                "4": "https://uploads.overwolf.com/owclient/direct/2024/07/24/1ee29237-2e60-4d29-aaa1-107e73243b9b.mp4",
                "5": "https://uploads.overwolf.com/owclient/direct/2024/07/24/61fe627a-ce4f-4246-9ae7-a8cc183f3706.mp4",
                "6": "https://uploads.overwolf.com/owclient/direct/2024/07/24/051c8b8d-664b-4600-b7cb-e9996ad0b14c.mp4",
                "7": "https://uploads.overwolf.com/owclient/direct/2024/07/24/bf5b351a-7ead-4f18-9fb3-f340ff3d1a1b.mp4",
                "8": "https://uploads.overwolf.com/owclient/direct/2024/07/24/3ee61967-b99d-4c71-86ef-d7863295971e.mp4",
                "9": "https://uploads.overwolf.com/owclient/direct/2024/07/24/9d81f5ef-819d-4455-b97e-2891223bc4b3.mp4",
                "10": "https://uploads.overwolf.com/owclient/direct/2024/07/24/3134c90f-32ff-43f6-ba7a-0ed25c216255.mp4",
                "11": "https://uploads.overwolf.com/owclient/direct/2024/07/24/bc2924ca-06cf-40cd-89c4-70bb8f558def.mp4",
                "12": "https://uploads.overwolf.com/owclient/direct/2024/07/24/b23ce2a1-ca49-43de-8120-49cd47151d66.mp4"
            }
        },
        "Sono_Bisque_Doll_wa_Koi_wo_Suru": {
            "title": "Sono Bisque Doll wa Koi wo Suru",
            "imagen": "https://telegra.ph/file/02b0f647b8ff6582b7cbc.jpg",
            "sinopsis": "El estudiante de secundaria Wakana Gojou pasa sus días perfeccionando el arte de hacer muñecas hina, con la esperanza de alcanzar eventualmente el nivel de experiencia de su abuelo. Mientras sus compañeros adolescentes se ocupan de la cultura pop, Gojou encuentra la felicidad en coser ropa para sus muñecas. Sin embargo, hace todo lo posible para mantener su pasatiempo único en secreto, ya que cree que sería ridiculizado si se revelara.\n\nEntra Marin Kitagawa, una chica extraordinariamente bonita cuya confianza y aplomo contrastan marcadamente con la mansedumbre de Gojou. Sería un desafío al sentido común que Gojou, sin amigos, se mezclara con gente como Kitagawa, que siempre está rodeada de sus compañeros. Sin embargo, sucede lo inimaginable cuando Kitagawa descubre la destreza de Gojou con una máquina de coser y le confiesa alegremente sobre su propio pasatiempo: el cosplay. Debido a que sus habilidades de costura son lamentables, decide solicitar su ayuda.\n\nMientras Gojou y Kitagawa trabajan juntos en un disfraz de cosplay tras otro, no pueden evitar volverse cercanos, a pesar de que sus vidas son mundos aparte.",
            "cap_total": 12,
            "temporada": 1,
            "clasificacion": "#romance",
            "capitulos": {
                "1": "https://uploads.overwolf.com/owclient/direct/2024/07/23/a7dde9e1-13d7-4bb0-ac4d-9146c9c1e18f.mp4",
                "2": "https://uploads.overwolf.com/owclient/direct/2024/07/23/6b821908-e4b8-4279-9a3c-4921ba1a1f32.mp4",
                "3": "https://uploads.overwolf.com/owclient/direct/2024/07/23/bfe5f0c8-099a-44e7-a283-66ae31402827.mp4",
                "4": "https://uploads.overwolf.com/owclient/direct/2024/07/23/1da11139-b29f-430e-a42f-3fc48466e32e.mp4",
                "5": "https://uploads.overwolf.com/owclient/direct/2024/07/23/0839da1b-543f-47ee-a969-82e20488c275.mp4",
                "6": "https://uploads.overwolf.com/owclient/direct/2024/07/23/c7145983-017d-4f47-924c-182ed2c5efc4.mp4",
                "7": "https://uploads.overwolf.com/owclient/direct/2024/07/23/e0ed0386-55f6-4185-afc1-6da021898f85.mp4",
                "8": "https://uploads.overwolf.com/owclient/direct/2024/07/23/7d56cacc-7628-482b-b6b9-93f65b3dddaf.mp4",
                "9": "https://uploads.overwolf.com/owclient/direct/2024/07/23/5ef96a48-29f3-4ba9-9e32-70aebbf5e8a5.mp4",
                "10": "https://uploads.overwolf.com/owclient/direct/2024/07/23/678ec280-4370-4486-8947-b2a5ecc1d915.mp4",
                "11": "https://uploads.overwolf.com/owclient/direct/2024/07/23/e403e2b3-6fb5-431b-add5-ab5258fe8e58.mp4",
                "12": "https://uploads.overwolf.com/owclient/direct/2024/07/23/707e5be6-4b07-4d07-bc0c-5a6c48333013.mp4"
            }
        },
        "Spy_x_Family": {
            "title": "Spy x Family",
            "imagen": "https://telegra.ph/file/dfb869c72875f9ae81a29.jpg",
            "sinopsis": "Políticos corruptos, nacionalistas frenéticos y otras fuerzas belicistas ponen constantemente en peligro la delgada capa de paz entre los países vecinos de Ostania y Westalis. A pesar de sus conspiraciones, el famoso espía y maestro del disfraz \"Twilight\" cumple peligrosas misiones una tras otra con la esperanza de que ningún niño tenga que experimentar los horrores de la guerra.\n\nEn la bulliciosa ciudad ostaniana de Berlint, Twilight adopta el alias de \"Loid Forger\", un estimado psiquiatra. Sin embargo, su verdadera intención es recabar información sobre el destacado político Donovan Desmond, que rara vez aparece en público en la escuela de sus hijos: la prestigiosa Academia Eden. Con la ayuda de la empleada soltera del ayuntamiento Yor Briar para que actúe como su esposa y adoptando a la curiosa huérfana de seis años Anya como su hija, Loid ejecuta su plan maestro. Inscribirá a Anya en la Academia Eden, donde Loid espera que destaque y le dé la oportunidad de conocer a Donovan sin despertar sospechas.\n\nDesafortunadamente para Loid, incluso un hombre con su talento tiene problemas para interpretar el papel de un padre y esposo amoroso. Y al igual que Loid oculta su verdadera identidad, Yor, que es una asesina clandestina conocida como \"La Princesa Espina\", y Anya, una esper que puede leer las mentes de las personas, tampoco tienen planes de revelar sus propios secretos. Aunque esta familia perfecta se basa en el engaño, los Forgers gradualmente comprenden que el amor que comparten supera todo lo demás.",
            "cap_total": 37,
            "temporada": 1,
            "clasificacion": "#Acción #Premiada #Comedia",
            "capitulos": {
                "1": "https://uploads.overwolf.com/owclient/direct/2024/07/23/3aa998af-0fa6-4117-ab30-e6875759dc41.mp4",
                "2": "https://uploads.overwolf.com/owclient/direct/2024/07/23/fadec0de-7dc2-4f9e-8f8e-823513c11d6b.mp4",
                "3": "https://uploads.overwolf.com/owclient/direct/2024/07/23/d555b5ae-b8fb-4097-a8f1-00b7cb1ef5cb.mp4",
                "4": "https://uploads.overwolf.com/owclient/direct/2024/07/23/247b6b93-3302-463d-acfe-4065a1b1a54a.mp4",
                "5": "https://uploads.overwolf.com/owclient/direct/2024/07/23/c7a4e4f0-6d97-49ac-99bd-bece2add3197.mp4",
                "6": "https://uploads.overwolf.com/owclient/direct/2024/07/23/52518096-9fea-4285-af32-7eabb3fe7afe.mp4",
                "7": "https://uploads.overwolf.com/owclient/direct/2024/07/23/44cd65d8-5ec1-4e9d-914e-f32b93bfb305.mp4",
                "8": "https://uploads.overwolf.com/owclient/direct/2024/07/23/25692cdb-8aeb-44fb-9cef-11000c2fd6a1.mp4",
                "9": "https://uploads.overwolf.com/owclient/direct/2024/07/23/a94be8d3-1816-4e4c-89ab-f0be1760ae46.mp4",
                "10": "https://uploads.overwolf.com/owclient/direct/2024/07/23/1dc04ffc-1477-417e-aae8-8af923595b92.mp4",
                "11": "https://uploads.overwolf.com/owclient/direct/2024/07/23/c0e033c7-455e-4103-967f-710fd17e7229.mp4",
                "12": "https://uploads.overwolf.com/owclient/direct/2024/07/23/974f9e7e-89f6-4600-8f6a-f3dec4b7558f.mp4",
                "13": "https://uploads.overwolf.com/owclient/direct/2024/07/23/2c762979-0ce9-4499-9bf8-a87fe99ca4f7.mp4",
                "14": "https://uploads.overwolf.com/owclient/direct/2024/07/23/9c8795ca-e86f-41c9-afd6-2fc902dc7b26.mp4",
                "15": "https://uploads.overwolf.com/owclient/direct/2024/07/23/dbefbdf9-045e-490d-a31f-ccfc38903f6b.mp4",
                "16": "https://uploads.overwolf.com/owclient/direct/2024/07/23/7dfa9d8f-a21e-4d81-89be-db721cb6f8b8.mp4",
                "17": "https://uploads.overwolf.com/owclient/direct/2024/07/23/7c9e70d6-bb79-471c-8a03-d181f2fd93fc.mp4",
                "18": "https://uploads.overwolf.com/owclient/direct/2024/07/23/ac17d8cc-3952-48c1-9c34-3b7fa2c71f82.mp4",
                "19": "https://uploads.overwolf.com/owclient/direct/2024/07/23/e6f323a8-b396-416b-ae36-db7bd5ce902f.mp4",
                "20": "https://uploads.overwolf.com/owclient/direct/2024/07/23/79b15102-c888-4702-a52a-b422f065a001.mp4",
                "21": "https://uploads.overwolf.com/owclient/direct/2024/07/23/16582606-c7e8-46e3-a59d-944e0477daed.mp4",
                "22": "https://uploads.overwolf.com/owclient/direct/2024/07/23/8a176088-17a7-4929-b690-944fcea8f070.mp4",
                "23": "https://uploads.overwolf.com/owclient/direct/2024/07/23/0adc514e-3184-47b4-ac18-48ef9f11cf6e.mp4",
                "24": "https://uploads.overwolf.com/owclient/direct/2024/07/23/5540dcc1-54bf-44ba-ade3-053b0db1093a.mp4",
                "25": "https://uploads.overwolf.com/owclient/direct/2024/07/23/77080c0a-9ecb-465a-866b-483f4ac29ddd.mp4",
                "26": "https://uploads.overwolf.com/owclient/direct/2024/07/23/1166966a-a9ba-4fe1-ab0f-6976d5787a9b.mp4",
                "27": "https://uploads.overwolf.com/owclient/direct/2024/07/23/a2cdf966-ff3a-4288-a9e5-83dd54ae0e26.mp4",
                "28": "https://uploads.overwolf.com/owclient/direct/2024/07/23/cf1d673b-0eab-46cc-b033-c718d9d37f63.mp4",
                "29": "https://uploads.overwolf.com/owclient/direct/2024/07/23/bc7b2ecc-60b2-4975-b5d7-dd7278c8d9e7.mp4",
                "30": "https://uploads.overwolf.com/owclient/direct/2024/07/23/bef8e18d-b921-4f4a-96a4-6bab8e7102a3.mp4",
                "31": "https://uploads.overwolf.com/owclient/direct/2024/07/23/a21fd220-ba54-4273-8ca9-100aa70c9a96.mp4",
                "32": "https://uploads.overwolf.com/owclient/direct/2024/07/23/5bf9b9e8-fdd6-473e-a56b-e73959e08834.mp4",
                "33": "https://uploads.overwolf.com/owclient/direct/2024/07/23/aa917b84-4f5a-440e-aeed-f749f3265f48.mp4",
                "34": "https://uploads.overwolf.com/owclient/direct/2024/07/23/ee1859d9-9352-4052-9ba1-baca06f2b2ed.mp4",
                "35": "https://uploads.overwolf.com/owclient/direct/2024/07/23/e919b529-266a-43da-8650-eafdfc676ba5.mp4",
                "36": "https://uploads.overwolf.com/owclient/direct/2024/07/23/5f658c5b-461a-4a0e-a9ae-9638de3b6a96.mp4",
                "37": "https://uploads.overwolf.com/owclient/direct/2024/07/23/83517f22-ab91-42cc-94b7-d82317f5cd88.mp4"
            }
        },
        "Watashi_no_Yuri_wa_Oshigoto_desu!": {
            "title": "Watashi no Yuri wa Oshigoto desu!",
            "imagen": "https://telegra.ph/file/25c5c01f361807f766dbc.jpg",
            "sinopsis": "Hime Shiraki parece tenerlo todo: una voz angelical, una personalidad inocente y un rostro adorable que enamora a todos los espectadores. Sin embargo, su ternura es una mentira: es puramente un acto para lograr su objetivo egocéntrico de casarse con un pretendiente rico. Aunque a menudo hace alarde de su inocencia para ganarse el favor de quienes la rodean, la fachada de Hime no la absuelve de la responsabilidad cuando un accidente deja a Mai Koshiba herida.\n\nAl enterarse de que Mai es la gerente de Café Liebe, un café con temática de academia solo para chicas, Hime se ve obligada a aceptar un puesto a tiempo parcial hasta que Mai se recupere. Sin embargo, la fachada de Hime no puede ocultar sus defectos como camarera, lo que le gana la ira de una de sus compañeras de trabajo, Mitsuki Yano, la elegante \"onee-sama\" que a menudo reprende a Hime por sus errores. Mientras Hime lucha por adaptarse a su nuevo trabajo, además de la implacable hostilidad de Mitsuki, su verdadera personalidad comienza a filtrarse por las grietas.",
            "cap_total": 12,
            "temporada": 1,
            "clasificacion": "#Comedia #AmorDeChicas",
            "capitulos": {
                "1": "https://uploads.overwolf.com/owclient/direct/2024/07/23/e1eab8ff-250d-4155-95b3-c87d6f6c79e4.mp4",
                "2": "https://uploads.overwolf.com/owclient/direct/2024/07/23/9191c8ce-7167-4935-84bd-b754b80fa35c.mp4",
                "3": "https://uploads.overwolf.com/owclient/direct/2024/07/23/4409b82c-f394-4be9-b666-4e993cebd57d.mp4",
                "4": "https://uploads.overwolf.com/owclient/direct/2024/07/23/cf48a9f6-3929-4c10-8ab1-3d5fda2139c2.mp4",
                "5": "https://uploads.overwolf.com/owclient/direct/2024/07/23/d49a427f-cf7a-4428-a498-db16fdc327ee.mp4",
                "6": "https://uploads.overwolf.com/owclient/direct/2024/07/23/66b186e5-af99-4983-b861-3590e33aa37c.mp4",
                "7": "https://uploads.overwolf.com/owclient/direct/2024/07/23/32b38578-95a9-4203-bcad-62fc343b067c.mp4",
                "8": "https://uploads.overwolf.com/owclient/direct/2024/07/23/e2eff3f6-f8ff-4d1d-8a89-f575df7b25a2.mp4",
                "9": "https://uploads.overwolf.com/owclient/direct/2024/07/23/81593b47-6bfb-4cfa-8ecd-2636a5fb8407.mp4",
                "10": "https://uploads.overwolf.com/owclient/direct/2024/07/23/fa502312-5cae-42f9-81d2-ba22e672a81f.mp4",
                "11": "https://uploads.overwolf.com/owclient/direct/2024/07/23/6b355974-5570-4665-9bc4-3784cc672d57.mp4",
                "12": "https://uploads.overwolf.com/owclient/direct/2024/07/23/6816aee1-7ef2-4440-a07b-0e546fdbe93c.mp4"
            }
        },
        "Sousou_no_Frieren": {
            "title": "Sousou no Frieren",
            "imagen": "https://cdn-eu.anidb.net/images/main/295082.jpg",
            "sinopsis": "La maga elfa Frieren y sus valientes compañeros aventureros han derrotado al Rey Demonio y traído paz a la tierra. Con la gran lucha superada, cada uno toma su propio camino para vivir una vida tranquila. Pero como elfa, Frieren, casi inmortal, superará con creces a los demás miembros de su antiguo grupo. ¿Cómo aceptará la mortalidad de sus amigos? ¿Cómo puede encontrar satisfacción en su propia vida, y puede aprender a comprender lo que significa la vida para los humanos a su alrededor? Frieren comienza un nuevo viaje para encontrar la respuesta.",
            "temporada": 1,
            "clasificacion": "#Aventura #Fantasia #Drama",
            "cap_total": 28,
            "capitulos": {
                "1": "https://uploads.overwolf.com/owclient/direct/2024/07/22/55ab5ddb-4f65-4994-81e2-85345ff4fcfb.mp4",
                "2": "https://uploads.overwolf.com/owclient/direct/2024/07/22/f7258857-89bd-4963-acdc-c06d0845a96d.mp4",
                "3": "https://uploads.overwolf.com/owclient/direct/2024/07/22/a952a7ff-1ab7-4d6a-9cfe-7919237762d7.mp4",
                "4": "https://uploads.overwolf.com/owclient/direct/2024/07/22/8ae661a2-e325-42ef-a9e7-799ab6018713.mp4",
                "5": "https://uploads.overwolf.com/owclient/direct/2024/07/22/f92a6348-f063-4b19-a64c-47d0b2171a40.mp4",
                "6": "https://uploads.overwolf.com/owclient/direct/2024/07/22/3047c772-5b06-4bb1-9e96-6c9160ee9f06.mp4",
                "7": "https://uploads.overwolf.com/owclient/direct/2024/07/22/b07533c8-a0ad-484d-a3fe-633866d7c981.mp4",
                "8": "https://uploads.overwolf.com/owclient/direct/2024/07/22/9f165042-4688-4a00-bbde-b3da967707f2.mp4",
                "9": "https://uploads.overwolf.com/owclient/direct/2024/07/22/a945c4c4-9af1-4209-b917-96fbf3a1e170.mp4",
                "10": "https://uploads.overwolf.com/owclient/direct/2024/07/22/1f5d1359-91c9-46fb-8148-55ce1f8ebfb8.mp4",
                "11": "https://uploads.overwolf.com/owclient/direct/2024/07/22/9054f326-dd31-431a-80ab-aa10a7b1d13c.mp4",
                "12": "https://uploads.overwolf.com/owclient/direct/2024/07/22/06cae021-e870-470c-aa0c-6655385c0ba1.mp4",
                "13": "https://uploads.overwolf.com/owclient/direct/2024/07/22/b08e233f-fe35-49f6-8803-2866cb62c26b.mp4",
                "14": "https://uploads.overwolf.com/owclient/direct/2024/07/22/6503662f-3bdd-4cf7-9098-81ed5e6b23e4.mp4",
                "15": "https://uploads.overwolf.com/owclient/direct/2024/07/22/21dc135b-a7a7-4440-9185-35da58c34c9e.mp4",
                "16": "https://uploads.overwolf.com/owclient/direct/2024/07/22/108738bb-d3ac-4245-92c3-5eb93832b581.mp4",
                "17": "https://uploads.overwolf.com/owclient/direct/2024/07/22/3a5890fa-b3c9-4f46-b841-0a7ce244b956.mp4",
                "18": "https://uploads.overwolf.com/owclient/direct/2024/07/22/52bcbc45-d526-4443-a55e-672278027b20.mp4",
                "19": "https://uploads.overwolf.com/owclient/direct/2024/07/22/10eeee6b-b134-4f9e-aaae-1f9d074e68bb.mp4",
                "20": "https://uploads.overwolf.com/owclient/direct/2024/07/22/a4cb9292-4553-410b-8dd9-3292c9c6a08b.mp4",
                "21": "https://uploads.overwolf.com/owclient/direct/2024/07/22/a7339295-a455-4f10-a087-ba2558ba4f30.mp4",
                "22": "https://uploads.overwolf.com/owclient/direct/2024/07/22/9ed2d03c-f1f9-465f-8d6b-450d8289a1c7.mp4",
                "23": "https://uploads.overwolf.com/owclient/direct/2024/07/22/5fd4506d-8b1e-41ba-b078-c18f2189bdb8.mp4",
                "24": "https://uploads.overwolf.com/owclient/direct/2024/07/22/fae02200-e9df-499c-908e-bbb9ac8a9f29.mp4",
                "25": "https://uploads.overwolf.com/owclient/direct/2024/07/22/c95f3482-fe7c-470e-b2c5-ff35ed39280c.mp4",
                "26": "https://uploads.overwolf.com/owclient/direct/2024/07/22/a4dc0381-b30c-42b9-af4d-c77c73ce4062.mp4",
                "27": "https://uploads.overwolf.com/owclient/direct/2024/07/22/02f94bca-17f0-4195-9759-21bdbc9d348c.mp4",
                "28": "https://uploads.overwolf.com/owclient/direct/2024/07/22/9fb00549-5fc6-478d-8429-9fa0ad5a086d.mp4"
            }
        },
        "Re_Monster": {
            "title": "Re Monster",
            "imagen": "https://telegra.ph/file/abd2dfc5d38c098c9bfa5.jpg",
            "sinopsis": "Tomokui Kanata se ha reencarnado en el duende más débil, llamado Goburou, después de haber sufrido una muerte desafortunada. Sin embargo, Goburou ha conservado los recuerdos de su vida anterior, una evolución inusual, además de volverse lo suficientemente fuerte como para obtener mejoras de estado al comer.\n\nEn este mundo alternativo de supervivencia del más apto, los eventos se desarrollan con subordinados y camaradas competentes, un delicioso caso del perro que mueve la cola...",
            "cap_total": 12,
            "temporada": 1,
            "clasificacion": "#Acción #Aventura #Fantasía",
            "capitulos": {
                "1": "https://uploads.overwolf.com/owclient/direct/2024/07/22/e0ad5b9c-827f-4fa1-b508-0ec74cfad68b.mp4",
                "2": "https://uploads.overwolf.com/owclient/direct/2024/07/22/bb24dd17-05a8-493c-b02e-78d93ac367c0.mp4",
                "3": "https://uploads.overwolf.com/owclient/direct/2024/07/22/420a3eaf-9687-4c44-ad53-6be8624ea10b.mp4",
                "4": "https://uploads.overwolf.com/owclient/direct/2024/07/22/28d96941-8eaa-42a8-8070-283ed70482d9.mp4",
                "5": "https://uploads.overwolf.com/owclient/direct/2024/07/22/bd764679-c217-4fe9-9633-6f5ac5d6888b.mp4",
                "6": "https://uploads.overwolf.com/owclient/direct/2024/07/22/b08ad2ff-d01d-4c8c-9165-02fcecd9e77d.mp4",
                "7": "https://uploads.overwolf.com/owclient/direct/2024/07/22/79743714-d18a-42b2-8292-a3081ef6d03d.mp4",
                "8": "https://uploads.overwolf.com/owclient/direct/2024/07/22/181782f9-bfcf-4f5a-9212-346cd1295bbf.mp4",
                "9": "https://uploads.overwolf.com/owclient/direct/2024/07/22/6f4007f0-b636-4e44-a4fd-874bb92a22fa.mp4",
                "10": "https://uploads.overwolf.com/owclient/direct/2024/07/22/e8c3078c-d116-44a8-ad12-440829b0b7e5.mp4",
                "11": "https://uploads.overwolf.com/owclient/direct/2024/07/22/862109ce-57a5-4fed-9589-3248725dc38e.mp4",
                "12": "https://uploads.overwolf.com/owclient/direct/2024/07/22/ecae9520-ceb7-4946-978c-a25d60920b49.mp4"
            }
        },
        "Kaijuu_8-gou": {
            "title": "Kaijuu 8-gou",
            "imagen": "https://telegra.ph/file/d6317e14be0484bf69bd7.jpg",
            "sinopsis": "Después de la destrucción de su ciudad natal, los amigos de la infancia Kafka Hibino y Mina Ashiro hacen un pacto para convertirse en oficiales de la Fuerza de Defensa, una organización militarizada encargada de proteger a Japón de monstruos colosales conocidos como \"kaijuu\". Décadas más tarde, Kafka, de 32 años, prácticamente ha renunciado a sus sueños de heroísmo. En cambio, limpia los restos de los kaijuu asesinados después de que son derrotados por valientes soldados, incluida Mina, quien ha logrado con éxito su objetivo compartido.\n\nAlconocer a su nuevo compañero de trabajo, Reno Ichikawa, Kafka se enfrenta a un espejo de su yo pasado: un joven ambicioso cuyo único deseo es luchar como miembro de la Fuerza de Defensa. Desafortunadamente, los dos pronto se ven involucrados en un extraño encuentro con un kaijuu rebelde. Aunque Kafka demuestra su naturaleza heroica innata y rescata a Reno de una perdición segura, queda gravemente herido.\n\nMientras ambos hombres se recuperan en un hospital, Kafka aparentemente es atacado por otra de las bestias. Como resultado, obtiene la habilidad de transformarse en un kaiju humanoide con la fuerza y los poderes de los monstruos gigantescos que amenazan a Japón. Apodado \"Kaijuu No. 8\" por los militares, Kafka decide usar sus nuevos dones para el bien común. Unidos por el respeto mutuo, Kafka y Reno se proponen unirse a guerreros como Mina en la vanguardia de la Fuerza de Defensa.",
            "cap_total": 12,
            "temporada": 1,
            "clasificacion": "#Acción #Ciencia #ficción",
            "capitulos": {
                "1": "https://uploads.overwolf.com/owclient/direct/2024/07/14/161e8fc4-db1e-454c-854d-257afbda6995.mp4",
                "2": "https://uploads.overwolf.com/owclient/direct/2024/07/14/a234de35-366a-4084-bade-c058eeb823d1.mp4",
                "3": "https://uploads.overwolf.com/owclient/direct/2024/07/14/b46c0b77-895a-467a-b5f2-4e66c055f207.mp4",
                "4": "https://uploads.overwolf.com/owclient/direct/2024/07/14/4f841164-11fe-4620-bbf1-e4098b412de4.mp4",
                "5": "https://uploads.overwolf.com/owclient/direct/2024/07/14/9f20fe29-fc3d-41b3-a281-a17bfc9726dc.mp4",
                "6": "https://uploads.overwolf.com/owclient/direct/2024/07/14/426b927e-0ec4-4e39-acd7-5b896fc0c23f.mp4",
                "7": "https://uploads.overwolf.com/owclient/direct/2024/07/14/838e2965-26e0-490a-99fe-83da8dd3aafc.mp4",
                "8": "https://uploads.overwolf.com/owclient/direct/2024/07/14/9467d6ce-7e65-4eba-8888-f8ba2ea1e135.mp4",
                "9": "https://uploads.overwolf.com/owclient/direct/2024/07/14/83243f35-acbd-41a3-954a-9b855c45b6ea.mp4",
                "10": "https://uploads.overwolf.com/owclient/direct/2024/07/14/a2d28257-f920-4e89-9803-71f4a3286bd6.mp4",
                "11": "https://uploads.overwolf.com/owclient/direct/2024/07/14/c69f46da-88e7-4060-9af8-5d71ba7249ac.mp4",
                "12": "https://uploads.overwolf.com/owclient/direct/2024/07/14/06ca8b8e-1f2c-4ebf-8d52-c3cc41fc2309.mp4"
            }
        }
    },
    "hentais": {
        "Kazoku:_Haha_to_Shimai_no_Kyousei": {
            "title": "Kazoku: Haha to Shimai no Kyousei",
            "imagen": "https://telegra.ph/file/c3b86c647d31b7d7a3ee5.jpg",
            "sinopsis": "",
            "cap_total": 5,
            "temporada": 1,
            "clasificacion": "#NTR #Incesto",
            "capitulos": {
                "1": "https://uploads.overwolf.com/owclient/direct/2024/08/01/8703b50c-794b-4582-9960-62d43b60760c.mp4",
                "2": "https://uploads.overwolf.com/owclient/direct/2024/08/01/aa67ee1a-174f-41a9-97e5-2dd6eb542e77.mp4",
                "3": "https://uploads.overwolf.com/owclient/direct/2024/08/01/99b14cff-9a78-4ddc-b3f7-754effb47109.mp4",
                "4": "https://uploads.overwolf.com/owclient/direct/2024/08/01/c8b8a015-e0cb-4f26-bc2f-0edb3d2da7a2.mp4",
                "5": "https://uploads.overwolf.com/owclient/direct/2024/08/01/006796cf-19d4-4c68-837f-6aa52f2e98fa.mp4"
            }
        },
        "Ito_o_Yoru": {
            "title": "Ito o Yoru",
            "imagen": "https://telegra.ph/file/6554e4ff9dcc780c6b8b9.jpg",
            "sinopsis": "",
            "cap_total": 1,
            "temporada": 1,
            "clasificacion": "#Colegiala",
            "capitulos": {
                "1": "https://uploads.overwolf.com/owclient/direct/2024/08/01/aafba18d-ff4e-4a97-ad8b-75923ffd0817.mp4"
            }
        },
        "Natsu_ga_Owaru_made_Natsu_no_Owari_The_Animation": {
            "title": "Natsu ga Owaru made: Natsu no Owari The Animation",
            "imagen": "https://cdn-eu.anidb.net/images/main/302735.jpg",
            "sinopsis": "",
            "cap_total": 2,
            "temporada": 1,
            "clasificacion": "#NTR #Colegiala",
            "capitulos": {
                "1": "https://uploads.overwolf.com/owclient/direct/2024/07/07/9ffc1b58-e97c-4db6-a750-49e053c00fb8.mp4",
                "2": "https://uploads.overwolf.com/owclient/direct/2024/08/01/361bd9c4-9c44-47bc-9f28-29c1744eb13a.mp4"
            }
        },
        "Mugoku_no_Kuni_no_Alice": {
            "title": "Mugoku no Kuni no Alice",
            "imagen": "https://cdn-eu.anidb.net/images/main/302922.jpg",
            "sinopsis": "",
            "temporada": 1,
            "clasificacion": "#Bestialismo #Fantasia #Violación",
            "cap_total": 2,
            "capitulos": {
                "1": "https://uploads.overwolf.com/owclient/direct/2024/06/20/f7b710b1-a45c-4d4a-8e94-1c4acdb82f40.mp4",
                "2": "https://uploads.overwolf.com/owclient/direct/2024/08/01/a168cb0c-9c4f-4865-b666-847f553f4338.mp4"
            }
        },
        "Succubus_Connect": {
            "title": "Succubus Connect",
            "imagen": "https://cdn-eu.anidb.net/images/main/302385.jpg",
            "sinopsis": "",
            "temporada": 1,
            "clasificacion": "#Fantasia #Sucubos",
            "cap_total": 2,
            "capitulos": {
                "1": "https://uploads.overwolf.com/owclient/direct/2024/05/07/8d68d2fa-b134-474d-9221-d51b9fcc9195.mp4",
                "2": "https://uploads.overwolf.com/owclient/direct/2024/08/01/7174a00a-7d87-4c0b-a09d-b137071fe305.mp4"
            }
        },
        "Seiyoku_Tsuyo_Tsuyo_The_Animation": {
            "title": "Seiyoku Tsuyo Tsuyo The Animation",
            "imagen": "https://cdn-eu.anidb.net/images/main/304082.jpg",
            "sinopsis": "",
            "temporada": 1,
            "clasificacion": "#NTR #Colegiala",
            "cap_total": 2,
            "capitulos": {
                "1": "https://uploads.overwolf.com/owclient/direct/2024/08/01/c2eec6d5-4888-491a-839a-13bd83dcc862.mp4",
                "2": "https://uploads.overwolf.com/owclient/direct/2024/08/01/911761bf-7319-4df7-9e1e-5d29e01a1e2d.mp4"
            }
        },
        "Boku_ni_Harem_Sexfriend_ga_Dekita_Riyuu": {
            "title": "Boku ni Harem Sexfriend ga Dekita Riyuu",
            "imagen": "https://cdn-eu.anidb.net/images/main/303860.jpg",
            "sinopsis": "",
            "temporada": 1,
            "clasificacion": "#Colegiala #Harem",
            "cap_total": 4,
            "capitulos": {
                "1": "https://uploads.overwolf.com/owclient/direct/2024/07/27/6c49a141-0c94-4cc3-b6f6-5b3bab218166.mp4",
                "2": "https://uploads.overwolf.com/owclient/direct/2024/07/27/566a750a-7e1b-4a8f-a8e1-887660a85050.mp4",
                "3": "https://uploads.overwolf.com/owclient/direct/2024/07/31/a8b0f7a8-c2de-48b4-bf40-7a3e9b7f3e6a.mp4",
                "4": "https://uploads.overwolf.com/owclient/direct/2024/07/26/c872110c-c4ce-4891-8ae0-45736aa26b17.mp4"
            }
        },
        "Enjo_Kouhai": {
            "title": "Enjo Kouhai",
            "imagen": "https://cdn-eu.anidb.net/images/main/240599.jpg",
            "sinopsis": "",
            "temporada": 1,
            "clasificacion": "#Fantasía #Harem #Semihumanas #Violación",
            "cap_total": 9,
            "capitulos": {
                "1": "https://uploads.overwolf.com/owclient/direct/2024/07/06/000a8ba9-0cc5-4eb1-9940-d312dbed3bc3.mp4",
                "2": "https://uploads.overwolf.com/owclient/direct/2024/07/06/15353381-5c23-4341-8e2d-24cf0bc0bed8.mp4",
                "3": "https://uploads.overwolf.com/owclient/direct/2024/07/06/b040c199-de95-46a1-a1b4-1a9263f80ba6.mp4",
                "4": "https://uploads.overwolf.com/owclient/direct/2024/07/06/afddf38c-27e1-4732-8882-7a4be9d6b201.mp4",
                "5": "https://uploads.overwolf.com/owclient/direct/2024/07/06/218b8015-1792-4b4f-b380-3368eb5efb90.mp4",
                "6": "https://uploads.overwolf.com/owclient/direct/2024/07/06/da630f22-6a9a-4325-9802-65044fe57f83.mp4",
                "7": "https://uploads.overwolf.com/owclient/direct/2024/07/06/f0ec6302-ec63-47f8-bc47-d61b6cf157f3.mp4",
                "8": "https://uploads.overwolf.com/owclient/direct/2024/07/06/94369a32-ec9e-4ff5-ad42-2a3fb28143ce.mp4",
                "9": "https://uploads.overwolf.com/owclient/direct/2024/07/10/79173dce-20a7-4757-bdc7-6b5bb541dfb6.mp4"
            }
        },
        "Gobaku_Moe_Mama_Tsurezure": {
            "title": "Gobaku: Moe Mama Tsurezure",
            "imagen": "https://cdn-eu.anidb.net/images/main/304295.jpg",
            "sinopsis": "",
            "temporada": 1,
            "clasificacion": "#NTR #Milf",
            "cap_total": 1,
            "capitulos": {
                "1": "https://uploads.overwolf.com/owclient/direct/2024/07/24/4b419958-a685-4972-845a-6da6995d1b8e.mp4"
            }
        },
        "Sefure_no_Senpai_The_Animation": {
            "title": "Sefure no Senpai The Animation",
            "imagen": "https://cdn-eu.anidb.net/images/main/303320.jpg",
            "sinopsis": "",
            "temporada": 1,
            "clasificacion": "#Vanilla",
            "cap_total": 2,
            "capitulos": {
                "1": "https://uploads.overwolf.com/owclient/direct/2024/07/06/57272438-01d5-4c92-a401-ef4c349f1133.mp4",
                "2": "https://uploads.overwolf.com/owclient/direct/2024/07/06/5b3d8c94-5465-47c8-be42-7c64a3892709.mp4"
            }
        },
        "NocturnaL": {
            "title": "NocturnaL",
            "imagen": "https://cdn-eu.anidb.net/images/main/300268.jpg",
            "sinopsis": "",
            "temporada": 1,
            "clasificacion": "#Colegiala #Romance",
            "cap_total": 2,
            "capitulos": {
                "1": "https://uploads.overwolf.com/owclient/direct/2024/05/07/2b220e44-aab3-4fba-898f-5e17ec8905db.mp4",
                "2": "https://uploads.overwolf.com/owclient/direct/2024/07/16/a1b3b9eb-7ae7-49a4-95a0-06983c5eb75e.mp4"
            }
        },
        "No_Wife_No_Life!": {
            "title": "No Wife No Life!",
            "imagen": "https://cdn-eu.anidb.net/images/main/296153.jpg",
            "sinopsis": "",
            "temporada": 1,
            "clasificacion": "#NTR #Milf #Tetonas",
            "cap_total": 2,
            "capitulos": {
                "1": "https://uploads.overwolf.com/owclient/direct/2024/03/14/90c4bdca-e2f1-4041-87a5-ba395012d94c.mp4",
                "2": "https://uploads.overwolf.com/owclient/direct/2024/07/19/b80bb95c-c197-4d57-9633-fec6f16fcf8a.mp4"
            }
        },
        "Yarakashi": {
            "title": "Yarakashi",
            "imagen": "https://cdn-eu.anidb.net/images/main/304294.jpg",
            "sinopsis": "",
            "temporada": 1,
            "clasificacion": "#NTR",
            "cap_total": 1,
            "capitulos": {
                "1": "https://uploads.overwolf.com/owclient/direct/2024/07/21/45c86618-4207-446b-abb3-504f361eb5aa.mp4"
            }
        },
        "Katei_Kyoushi_x_Saimin_2_The_Animation": {
            "title": "Katei Kyoushi x Saimin 2 The Animation",
            "imagen": "https://cdn-eu.anidb.net/images/main/299011.jpg",
            "sinopsis": "",
            "temporada": 1,
            "clasificacion": "#ControlMental #Milf #Tetonas",
            "cap_total": 2,
            "capitulos": {
                "1": "https://uploads.overwolf.com/owclient/direct/2024/05/11/778c3a79-7b32-4c24-9c11-6d4638a39bca.mp4",
                "2": "https://uploads.overwolf.com/owclient/direct/2024/07/14/d0a606f7-db30-48ab-9e6d-25a0167d3c93.mp4"
            }
        },
        "Tsuma_o_Dousoukai_ni_Ikasetara": {
            "title": "Tsuma o Dousoukai ni Ikasetara",
            "imagen": "https://cdn-eu.anidb.net/images/main/300363.jpg",
            "sinopsis": "",
            "temporada": 1,
            "clasificacion": "#NTR",
            "cap_total": 1,
            "capitulos": {
                "1": "https://uploads.overwolf.com/owclient/direct/2024/07/12/60af5947-b465-4d11-84c1-8ea23ee5530d.mp4"
            }
        },
        "Konomi_ja_Nai_kedo_Mukatsuku_Ane_to_Aishou_Batsugun_Ecchi": {
            "title": "Konomi ja Nai kedo: Mukatsuku Ane to Aishou Batsugun Ecchi",
            "imagen": "https://cdn-eu.anidb.net/images/main/298605.jpg",
            "sinopsis": "",
            "temporada": 1,
            "clasificacion": "#Colegiala #Incesto",
            "cap_total": 2,
            "capitulos": {
                "1": "https://uploads.overwolf.com/owclient/direct/2024/07/07/41c02c05-2588-4b2e-989f-6454b119bcba.mp4",
                "2": "https://uploads.overwolf.com/owclient/direct/2024/07/07/e11719c3-d419-4149-8305-94eab5e72c45.mp4"
            }
        },
        "Sakusei_Byoutou": {
            "title": "Sakusei Byoutou",
            "imagen": "https://cdn-eu.anidb.net/images/main/285990.jpg",
            "sinopsis": "",
            "temporada": 1,
            "clasificacion": "#Enfermera",
            "cap_total": 8,
            "capitulos": {
                "1": "https://uploads.overwolf.com/owclient/direct/2024/06/14/8588b35f-5040-4c4e-92fa-141e0d3e589e.mp4",
                "2": "https://uploads.overwolf.com/owclient/direct/2024/06/14/27f7d475-c695-4ae2-9cfd-0e5af50c15b6.mp4",
                "3": "https://uploads.overwolf.com/owclient/direct/2024/06/14/cb7ff253-8418-4d93-88ca-e505639d71ea.mp4",
                "4": "https://uploads.overwolf.com/owclient/direct/2024/06/14/7472e5d1-a5ac-4c6c-8a64-6b55ce4c8638.mp4",
                "5": "https://uploads.overwolf.com/owclient/direct/2024/06/14/9e4ec0d8-66eb-44d9-bbfa-8332c90ab005.mp4",
                "6": "https://uploads.overwolf.com/owclient/direct/2024/06/14/79f7618b-ca06-4e42-945a-814683404679.mp4",
                "7": "https://uploads.overwolf.com/owclient/direct/2024/06/14/a4adaf1f-cf5e-4800-9a94-4c82d2dae9c0.mp4",
                "8": "https://uploads.overwolf.com/owclient/direct/2024/06/16/585b5587-8be0-4703-83fa-36e7ace31f26.mp4"
            }
        },
        "Kotowarenai_Haha": {
            "title": "Kotowarenai Haha",
            "imagen": "https://cdn-eu.anidb.net/images/main/297430.jpg",
            "sinopsis": "",
            "temporada": 1,
            "clasificacion": "#Milf",
            "cap_total": 2,
            "capitulos": {
                "1": "https://uploads.overwolf.com/owclient/direct/2024/04/10/d05798a7-97bd-4567-af04-15405ef065ba.mp4",
                "2": "https://uploads.overwolf.com/owclient/direct/2024/07/07/aa1a5247-026f-494b-9430-8a277da138cf.mp4"
            }
        },
        "Mebuki_The_Animation": {
            "title": "Mebuki The Animation",
            "imagen": "https://cdn-eu.anidb.net/images/main/298970.jpg",
            "sinopsis": "",
            "temporada": 1,
            "clasificacion": "#Colegiala #Violación",
            "cap_total": 2,
            "capitulos": {
                "1": "https://uploads.overwolf.com/owclient/direct/2024/05/07/9aa87a09-2cfc-42e9-949c-ab893da42cad.mp4",
                "2": "https://uploads.overwolf.com/owclient/direct/2024/06/25/5735148e-c8d8-4b77-9fd8-80b448ddcec3.mp4"
            }
        },
        "Ruins_Seeker": {
            "title": "Ruins Seeker",
            "imagen": "https://cdn-eu.anidb.net/images/main/302924.jpg",
            "sinopsis": "",
            "temporada": 1,
            "clasificacion": "#Bestialismo #Fantasía #Violación",
            "cap_total": 2,
            "capitulos": {
                "1": "https://uploads.overwolf.com/owclient/direct/2024/04/07/fd564bf0-13c3-49e8-ab0c-2fafcd47e6f7.mp4",
                "2": "https://uploads.overwolf.com/owclient/direct/2024/07/07/931508bb-96a1-4bf0-bfe9-84f08319d9a9.mp4"
            }
        },
        "Shuumatsu_Hospital": {
            "title": "Shuumatsu Hospital",
            "imagen": "https://cdn-eu.anidb.net/images/main/302923.jpg",
            "sinopsis": "",
            "temporada": 1,
            "clasificacion": "#NTR #Enfermera",
            "cap_total": 1,
            "capitulos": {
                "1": "https://uploads.overwolf.com/owclient/direct/2024/06/29/707da1be-b162-453a-b73d-b724995dbd93.mp4"
            }
        },
        "Kyonyuu_Onna_Shikan_Sennou_Saimin": {
            "title": "Kyonyuu Onna Shikan Sennou Saimin",
            "imagen": "https://telegra.ph/file/2e3aef802c82683f57125.jpg",
            "sinopsis": "",
            "cap_total": 2,
            "temporada": 1,
            "clasificacion": "#ControlMental #Tetonas #Harem",
            "capitulos": {
                "1": "https://uploads.overwolf.com/owclient/direct/2024/07/05/22c38125-1bf9-44cc-a69d-5a5623b7beb7.mp4",
                "2": "https://uploads.overwolf.com/owclient/direct/2024/07/05/c4ed2615-4de6-4485-b8f3-6e7b0a968075.mp4"
            }
        },
        "69_Itsuwari_no_Hohoe": {
            "title": "69: Itsuwari no Hohoe",
            "imagen": "https://telegra.ph/file/7241805ced53286a2b5f9.jpg",
            "sinopsis": "",
            "cap_total": 2,
            "temporada": 1,
            "clasificacion": "#Colegiala #Violación",
            "capitulos": {
                "1": "https://uploads.overwolf.com/owclient/direct/2024/03/25/3ce760ea-919a-448d-885f-2425ee7452cb.mp4",
                "2": "https://uploads.overwolf.com/owclient/direct/2024/05/22/fddab26a-e0fa-4c63-a168-2acd5968a8ff.mp4"
            }
        },
        "Rennyu_Order_The_Animation": {
            "title": "Rennyu Order The Animation",
            "imagen": "https://telegra.ph/file/6072ab71e2c23fe954d7f.jpg",
            "sinopsis": "",
            "cap_total": 1,
            "temporada": 1,
            "clasificacion": "#Vanilla #Tetonas",
            "capitulos": {
                "1": "https://uploads.overwolf.com/owclient/direct/2024/05/09/9c83ea3c-0c09-405a-a6be-199b4e74a161.mp4"
            }
        },
        "Dearest_Blue": {
            "title": "Dearest Blue",
            "imagen": "https://telegra.ph/file/5ec67c155c6e4be170d63.jpg",
            "sinopsis": "",
            "cap_total": 1,
            "temporada": 1,
            "clasificacion": "#Violación",
            "capitulos": {
                "1": "https://uploads.overwolf.com/owclient/direct/2024/07/07/1a720777-73bc-421b-aa87-75fc89e159de.mp4"
            }
        },
        "Midareuchi": {
            "title": "Midareuchi",
            "imagen": "https://telegra.ph/file/11ffa06bab4c9ed132db4.jpg",
            "sinopsis": "",
            "cap_total": 2,
            "temporada": 1,
            "clasificacion": "#NTR #Colegiala",
            "capitulos": {
                "1": "https://uploads.overwolf.com/owclient/direct/2024/07/07/af90faa9-d287-41b3-bbc4-737cf95fd5e2.mp4",
                "2": "https://uploads.overwolf.com/owclient/direct/2024/07/07/e4f8ed9d-2c5c-4e86-8b94-d2cf3ba60b3f.mp4"
            }
        },
        "1LDK+JK_Ikinari_Doukyo?_Micchaku!?_Hatsu_Ecchi!!?": {
            "title": "1LDK+JK Ikinari Doukyo? Micchaku!? Hatsu Ecchi!!?",
            "imagen": "https://telegra.ph/file/dc4de7ea6e563b53dfbcb.jpg",
            "sinopsis": "",
            "cap_total": 3,
            "temporada": 1,
            "clasificacion": "#Vanilla #Romance",
            "capitulos": {
                "1": "https://uploads.overwolf.com/owclient/direct/2024/07/06/6ec697a6-b13b-4e9b-898f-694869a1f299.mp4",
                "2": "https://uploads.overwolf.com/owclient/direct/2024/07/06/f49dd85b-b5ac-43eb-806b-a9b8433584e9.mp4",
                "3": "https://uploads.overwolf.com/owclient/direct/2024/07/06/f49dd85b-b5ac-43eb-806b-a9b8433584e9.mp4"
            }
        },
        "Shunkashuutou": {
            "title": "Shunkashuutou",
            "imagen": "https://telegra.ph/file/3f4ab485e8b4845f0cc0f.jpg",
            "sinopsis": "",
            "cap_total": 2,
            "temporada": 1,
            "clasificacion": "#Colegiala #Violación",
            "capitulos": {
                "1": "https://uploads.overwolf.com/owclient/direct/2024/03/10/0e7563d0-4050-41cb-81e7-deb67914c90e.mp4",
                "2": "https://uploads.overwolf.com/owclient/direct/2024/04/18/3f165711-1333-4326-9d40-8ec26cc8bfcc.mp4"
            }
        },
        "Oji-san_de_Umeru_Ana_The_Animation": {
            "title": "Oji-san de Umeru Ana The Animation",
            "imagen": "https://telegra.ph/file/67485afd21a85773b1ffd.jpg",
            "sinopsis": "",
            "cap_total": 2,
            "temporada": 1,
            "clasificacion": "#Colegiala",
            "capitulos": {
                "1": "https://uploads.overwolf.com/owclient/direct/2024/04/03/d340d316-bd19-4bc1-8b28-fecd232d5f47.mp4",
                "2": "https://uploads.overwolf.com/owclient/direct/2024/04/03/c4cfd2c4-6991-4135-a7c7-ecd65c310502.mp4"
            }
        },
        "SiNiSistar": {
            "title": "SiNiSistar",
            "imagen": "https://telegra.ph/file/cf6c618f57e33a4b29291.jpg",
            "sinopsis": "",
            "cap_total": 2,
            "temporada": 1,
            "clasificacion": "#Bestialismo #Gore #Violación",
            "capitulos": {
                "1": "https://uploads.overwolf.com/owclient/direct/2024/03/04/0971763c-5dfe-4b38-96c7-904b0f399c9c.mp4",
                "2": "https://uploads.overwolf.com/owclient/direct/2024/04/06/75789ea7-b293-4331-b891-b67ade7dc042.mp4"
            }
        },
        "Mitasarete_Mezameru_Asa_ni": {
            "title": "Mitasarete Mezameru Asa ni",
            "imagen": "https://telegra.ph/file/37d66120340a4c04c85ff.jpg",
            "sinopsis": "",
            "cap_total": 1,
            "temporada": 1,
            "clasificacion": "#Vanilla #Romance",
            "capitulos": {
                "1": "https://uploads.overwolf.com/owclient/direct/2024/03/12/1642a32d-bd5c-48da-8764-7c6375645abe.mp4"
            }
        },
        "Hatsukoi_Time": {
            "title": "Hatsukoi Time",
            "imagen": "https://telegra.ph/file/ada50506418ca5d87de1f.jpg",
            "sinopsis": "",
            "cap_total": 6,
            "temporada": 1,
            "clasificacion": "#Vanilla #Romance",
            "capitulos": {
                "1": "https://uploads.overwolf.com/owclient/direct/2024/02/26/730c71bf-8563-4b57-9892-4d8d94b872a9.mp4",
                "2": "https://uploads.overwolf.com/owclient/direct/2024/02/26/79b25d2d-b513-4fbe-8a82-a470aefb0112.mp4",
                "3": "https://uploads.overwolf.com/owclient/direct/2024/02/26/58b9b984-368d-4d3d-ba35-0a524af64534.mp4",
                "4": "https://uploads.overwolf.com/owclient/direct/2024/02/26/9c57537d-cf24-490d-81ef-c6ec9fe56781.mp4",
                "5": "https://uploads.overwolf.com/owclient/direct/2024/03/11/327e0137-bbfe-4302-a258-fa0f4858e91b.mp4",
                "6": "https://uploads.overwolf.com/owclient/direct/2024/03/11/057c4812-ff84-43c9-87ce-0e086a9daeed.mp4"
            }
        },
        "Shijoku_Zukushi": {
            "title": "Shijoku Zukushi",
            "imagen": "https://telegra.ph/file/c5049390a429d5947c8ed.jpg",
            "sinopsis": "",
            "cap_total": 2,
            "temporada": 1,
            "clasificacion": "#Incesto #NTR #Colegiala",
            "capitulos": {
                "1": "https://uploads.overwolf.com/owclient/direct/2024/03/09/e4b73622-6811-4f99-b827-1c957a80e7bc.mp4",
                "2": "https://uploads.overwolf.com/owclient/direct/2024/03/09/dffbc3dd-2932-40cf-8bc4-9ab87d0a2eee.mp4"
            }
        },
        "Doukyo_Suru_Neneki": {
            "title": "Doukyo Suru Neneki",
            "imagen": "https://telegra.ph/file/010482738ebc9468af2bb.jpg",
            "sinopsis": "",
            "cap_total": 2,
            "temporada": 1,
            "clasificacion": "#Fantasía #Semihumanas",
            "capitulos": {
                "1": "https://uploads.overwolf.com/owclient/direct/2024/03/08/c6691274-b69f-4e34-a3ab-b76d5056b43d.mp4",
                "2": "https://uploads.overwolf.com/owclient/direct/2024/03/08/c952114f-8871-4f1c-94f5-67f73c96f4e9.mp4"
            }
        },
        "Isekai_Kita_node_Sukebe_Skill_de_Zenryoku_Ouka_Shiyou_to_Omou_The_Animation": {
            "title": "Isekai Kita node Sukebe Skill de Zenryoku Ouka Shiyou to Omou The Animation",
            "imagen": "https://telegra.ph/file/266922c0f3e609707a264.jpg",
            "sinopsis": "",
            "cap_total": 4,
            "temporada": 1,
            "clasificacion": "#Comedia #Harem #Fantasía",
            "capitulos": {
                "1": "https://uploads.overwolf.com/owclient/direct/2024/03/07/0f91350b-3e69-4d27-8504-7f1b4c32ed64.mp4",
                "2": "https://uploads.overwolf.com/owclient/direct/2024/03/07/830633ea-05b6-46e7-af48-4288da5f6946.mp4",
                "3": "https://uploads.overwolf.com/owclient/direct/2024/03/07/7df1014c-8395-429a-b090-370c305d905e.mp4",
                "4": "https://uploads.overwolf.com/owclient/direct/2024/03/07/1fabb9ed-cad8-46ac-bf97-d13f30551076.mp4"
            }
        },
        "Fleur_The_Animation": {
            "title": "Fleur The Animation",
            "imagen": "https://telegra.ph/file/660293019b7d780580f51.jpg",
            "sinopsis": "",
            "cap_total": 1,
            "temporada": 1,
            "clasificacion": "#Romance",
            "capitulos": {
                "1": "https://uploads.overwolf.com/owclient/direct/2024/03/05/352d2668-4c34-4049-9b4a-88b9aef29578.mp4"
            }
        },
        "Doukyuusei_Remake_The_Animation": {
            "title": "Doukyuusei Remake The Animation",
            "imagen": "https://telegra.ph/file/39022af067104bf559808.jpg",
            "sinopsis": "",
            "cap_total": 2,
            "temporada": 1,
            "clasificacion": "#Romance #Colegiala",
            "capitulos": {
                "1": "https://uploads.overwolf.com/owclient/direct/2024/03/05/bfccd4f1-6bb5-4d4c-9993-b5803f478a47.mp4",
                "2": "https://uploads.overwolf.com/owclient/direct/2024/03/05/6a4e9cfc-b739-4ed1-ba73-ffc98453cfdb.mp4"
            }
        },
        "Mahou_Touki_Lyristia": {
            "title": "Mahou Touki Lyristia",
            "imagen": "https://telegra.ph/file/d88fa0de446b874ea7c99.jpg",
            "sinopsis": "",
            "cap_total": 2,
            "temporada": 1,
            "clasificacion": "#Violación",
            "capitulos": {
                "1": "https://uploads.overwolf.com/owclient/direct/2024/02/29/e52b8884-803f-4134-8072-43b4d97b1c80.mp4",
                "2": "https://uploads.overwolf.com/owclient/direct/2024/02/29/97d972a5-0b93-44f6-a5b3-c948185f010e.mp4"
            }
        },
        "Sweet_and_Hot": {
            "title": "Sweet and Hot",
            "imagen": "https://telegra.ph/file/40f14e16bcc0d5c93b40f.jpg",
            "sinopsis": "",
            "cap_total": 2,
            "temporada": 1,
            "clasificacion": "#Colegiala",
            "capitulos": {
                "1": "https://uploads.overwolf.com/owclient/direct/2024/03/25/36c8e918-81ee-4bee-945b-7c6e5c0c1ca5.mp4",
                "2": "https://uploads.overwolf.com/owclient/direct/2024/02/29/8d714794-939c-4ed6-9d5f-eaee18e25cef.mp4"
            }
        },
        "Mihitsu_no_Koi": {
            "title": "Mihitsu no Koi",
            "imagen": "https://telegra.ph/file/a8c058dd409d2c135c463.jpg",
            "sinopsis": "",
            "cap_total": 2,
            "temporada": 1,
            "clasificacion": "#Colegiala",
            "capitulos": {
                "1": "https://uploads.overwolf.com/owclient/direct/2024/02/29/7743f866-7c92-4711-a934-d0d320103259.mp4",
                "2": "https://uploads.overwolf.com/owclient/direct/2024/02/29/515de267-45ba-4688-aa22-683a6eb76efb.mp4"
            }
        }
    }
}